burla_io/__init__.py
burla_io-0.3.0.dist-info/METADATA
burla_io-0.3.0.dist-info/WHEEL
burla_io-0.3.0.dist-info/top_level.txt
burla_io-0.3.0.dist-info/RECORD
