Metadata-Version: 2.4
Name: burla_io
Version: 0.3.0
Summary: Utilities for Burla.dev (unofficial)
Author-email: Qingyun Li <qingy2019@outlook.com>
License: MIT
Project-URL: Homepage, https://github.com/Burla-Cloud/burla
Keywords: utils,itertools,contextmanager,testing
Classifier: Programming Language :: Python :: 3
Classifier: Programming Language :: Python :: 3 :: Only
Classifier: License :: OSI Approved :: MIT License
Classifier: Operating System :: OS Independent
Requires-Python: >=3.8
